dstools/__init__.py
dstools/classifier/BestGuessClassifier.py
dstools/classifier/__init__.py
dstools/preprocessing/Bucketizer.py
dstools/preprocessing/FeatureConverter.py
dstools/preprocessing/Imputer.py
dstools/preprocessing/NumScaler.py
dstools/preprocessing/OneHotEncoder.py
dstools/preprocessing/__init__.py
dstools/regressor/BestGuessRegressor.py
DataScienceTools-0.1.1.dev0.dist-info/LICENSE
DataScienceTools-0.1.1.dev0.dist-info/METADATA
DataScienceTools-0.1.1.dev0.dist-info/WHEEL
DataScienceTools-0.1.1.dev0.dist-info/top_level.txt
DataScienceTools-0.1.1.dev0.dist-info/RECORD
