Metadata-Version: 2.1
Name: DataScienceTools
Version: 0.1.1.dev0
Summary: UNKNOWN
Home-page: UNKNOWN
License: MIT License
Platform: UNKNOWN
Requires-Python: >3.5
Requires-Dist: numpy (>=1.16.2)
Requires-Dist: pandas (>=0.23.2)
Requires-Dist: scikit-learn (>=0.20.3)
Requires-Dist: statsmodels (>=0.9.0)
